{
  "Clients": {
    "open": true
  },
  "NetworkTables Settings": {
    "mode": "Client (NT3)",
    "serverTeam": "3357"
  },
  "Server": {
    "Publishers": {
      "open": true
    },
    "open": true
  },
  "VisionSubsystem@3": {
    "Publishers": {
      "open": true
    },
    "Subscribers": {
      "open": true
    },
    "open": true
  },
  "VisionSystem@2": {
    "Publishers": {
      "open": true
    },
    "Subscribers": {
      "open": true
    },
    "open": true
  },
  "example client@1": {
    "Publishers": {
      "open": true
    },
    "Subscribers": {
      "open": true
    },
    "open": true
  },
  "outlineviewer@3": {
    "Publishers": {
      "open": true
    },
    "Subscribers": {
      "open": true
    },
    "open": true
  },
  "transitory": {
    "datatable": {
      "open": true
    }
  }
}
